Metadata-Version: 2.0
Name: sonic182-logger
Version: 0.0.1
Summary: Logger utilities
Home-page: UNKNOWN
Author: Johanderson Mogollon
Author-email: johanderson@mogollon.com.ve
License: MIT
Platform: UNKNOWN
Provides-Extra: dev
Requires-Dist: attrs (==17.4.0); extra == 'dev'
Requires-Dist: coverage (==4.4.2); extra == 'dev'
Requires-Dist: pluggy (==0.6.0); extra == 'dev'
Requires-Dist: py (==1.5.2); extra == 'dev'
Requires-Dist: pytest-cov (==2.5.1); extra == 'dev'
Requires-Dist: pytest-sugar (==0.9.0); extra == 'dev'
Requires-Dist: pytest (==3.3.2); extra == 'dev'
Requires-Dist: six (==1.11.0); extra == 'dev'
Requires-Dist: termcolor (==1.1.0); extra == 'dev'
Provides-Extra: test
Requires-Dist: pytest; extra == 'test'
Requires-Dist: coverage; extra == 'test'
